erlcpy/__init__.py
erlcpy/main.py
erlcpy-1.1.6.dist-info/LICENSE
erlcpy-1.1.6.dist-info/METADATA
erlcpy-1.1.6.dist-info/WHEEL
erlcpy-1.1.6.dist-info/top_level.txt
erlcpy-1.1.6.dist-info/RECORD
